[
    {
        "ID":"101-2-1",
        "CollegeNum":101,
        "CollegeName":"艺术学院",
        "PlanNum":2,
        "PlanName":"演员的诞生",
        "PlanStage":1,
        "Auxli":[],
        "SubPlan":[
            {"PlanNume":"舞蹈"},
            {"PlanNume":"音乐表演（声乐）"},
            {"PlanNume":"表演"},
            {"PlanNume":"广播电视编导"},
            {"PlanNume":"舞蹈表演"}
        ],
        "CourseInfo":[
            {
                "CourseNum":"101158020",
                "CourseName":"声乐基础训练-1"
            },
            {
                "CourseNum":"101264030",
                "CourseName":"艺术语言基本技巧-1"
            },
            {
                "CourseNum":"101231020",
                "CourseName":"舞蹈与形体"
            },
            {
                "CourseNum":"101397070",
                "CourseName":"表演基础训练-1"
            },
            {
                "CourseNum":"101361030",
                "CourseName":"经典影片分析-1"
            },
            {
                "CourseNum":"101363030",
                "CourseName":"摄影与摄像-1"
            },
            {
                "CourseNum":"101364030",
                "CourseName":"视听语言-1"
            },
            {
                "CourseNum":"101858030",
                "CourseName":"影视文学创作-1"
            },
            {
                "CourseNum":"101368030",
                "CourseName":"影视美术基础-1"
            },
            {
                "CourseNum":"101870030",
                "CourseName":"微纪录创作实践-1"
            },
            {
                "CourseNum":"101003050",
                "CourseName":"芭蕾舞基本功训练-1"
            },
            {
                "CourseNum":"101227020",
                "CourseName":"舞蹈概论-1"
            },
            {
                "CourseNum":"101089020",
                "CourseName":"基础乐理"
            },
            {
                "CourseName":"中国古典身韵-1",
                "CourseNum":"101301020"
            },
            {
                "CourseName":"中国民族民间舞-1",
                "CourseNum":"101902020"
            },
            {
                "CourseName":"教学剧目-1",
                "CourseNum":"101097020"
            },
            {
                "CourseName": "专业主科课程-1",
                "CourseNum":"101333020"
            },
            {
                "CourseName":"视唱练耳-1",
                "CourseNum":"101171040"
            },
            {
                "CourseName":"钢琴-1",
                "CourseNum":"101431030"
            },
            {
                "CourseName":"伴奏课-1",
                "CourseNum":"101432020"
            },
            {
                "CourseName":"合唱（与合奏）-1",
                "CourseNum":"101624020"
            }
        ]
    },
    {
        "ID":"101-1-1",
        "CollegeNum":101,
        "CollegeName":"艺术学院",
        "PlanNum":1,
        "PlanName":"二次元伙伴",
        "PlanStage":1,
        "Auxli":[],
        "SubPlan":[
            {"PlanName":"动画"},
            {"PlanName":"视觉传达设计"}
        ],
        "CourseInfo":[
            {
                "CourseNum":"101832060",
                "CourseName":"素描"
            },
            {
                "CourseNum":"101833040",
                "CourseName":"装饰色彩"
            },
            {
                "CourseNum":"101409040",
                "CourseName":"动画概论"
            },
            {
                "CourseNum":"101440050",
                "CourseName":"数字绘画"
            },
            {
                "CourseNum":"101486020",
                "CourseName":"摄影基础"
            },
            {
                "CourseNum":"101256030",
                "CourseName":"艺术概论"
            },
            {
                "CourseNum":"101877040",
                "CourseName":"色彩"
            },
            {
                "CourseNum":"101966040",
                "CourseName":"计算机艺术设计软件"
            }
        ]
    },
    {
        "ID":"101-3-1",
        "CollegeNum":101,
        "CollegeName":"艺术学院",
        "PlanNum":3,
        "PlanName":"达芬奇二号",
        "PlanStage":1,
        "Auxli":[],
        "SubPlan":[
            {"PlanName":"环境设计"},
            {"PlanName":"绘画"},
            {"PlanName":"美术学"},
            {"PlanName":"书法学"},
            {"PlanName":"中国画"}
        ],
        "CourseInfo":[
            {
                "CourseName":"艺术概论",
                "CourseNum":"101256030"
            },
            {
                "CourseName":"书法",
                "CourseNum":"101185030"
            },
            {
                "CourseName":"隶书临摹",
                "CourseNum":"101887040"
            },
            {
                "CourseName":"楷书临摹",
                "CourseNum":"101890040"
            },
            {
                "CourseName":"中国书法史",
                "CourseNum":"101821030"
            },
            {
                "CourseName":"中国美术史-1（原始社会-唐朝）",
                "CourseNum":"101425040"
            },
            {
                "CourseName":"外国美术史-1（远古时代-文艺复兴）",
                "CourseNum":"101426040"
            },
            {
                "CourseName":"美术摄影基础",
                "CourseNum":"101113040"
            },
            {
                "CourseName":"素描-1（速写、静物、石膏头像、人物头像写生）",
                "CourseNum":"101421050"   
            },
            {
                "CourseName":"色彩-1（油画静物、人物头像写生）",
                "CourseNum":"101422050"
            },
            {
                "CourseName":"绘画透视学",
                "CourseNum":"101423030"
            },
            {
                "CourseName":"油画材料及绷布制底和美术画材研究(实践与实验报告方式体现)",
                "CourseNum":"101664010"
            },
            {
                "CourseName":"优秀美术作品观摹与研讨-1",
                "CourseNum":"101420010"
            },
            {
                "CourseName":"建筑与空间设计史论",
                "CourseNum":"101469020"
            },
            {
                "CourseName":"设计制图",
                "CourseNum":"101410030"
            },
            {
                "CourseName":"设计思维与表达训练1（造型能力训练）",
                "CourseNum":"101919040"
            },
            {
                "CourseName":"设计思维与表达训练2（色彩能力训练）",
                "CourseNum":"101920040"
            },
            {
                "CourseName":"计算机辅助设计1（photoshop indesign）",
                "CourseNum":"101921030"
            }
        ]
    },
    {
        "ID":"102-1-1",
        "CollegeNum":102,
        "CollegeName":"经济学院",
        "PlanNum":1,
        "PlanName":"炼金术士",
        "PlanStage":1,
        "Auxli":[],
        "SubPlan":[
            {"PlanName":"保险学"},
            {"PlanName":"财政学"},
            {"PlanName":"国际经济与贸易"},
            {"PlanName":"国际经济与贸易（双语班）"},
            {"PlanName":"国民经济管理"},
            {"PlanName":"金融工程"},
            {"PlanName":"金融学（双语班）"},
            {"PlanName":"金融学"},
            {"PlanName":"经济学"}
        ],
        "CourseInfo":[
            {
                "CourseName":"政治经济学",
                "CourseNum":"102566030"
            },
            {
                "CourseName":"经济法",
                "CourseNum":"102278020"
            },
            {
                "CourseName":"统计学",
                "CourseNum":"102132030"
            },
            {
                "CourseName":"金融数学",
                "CourseNum":"102174030"
            },
            {
                "CourseName":"统计学（全英文）",
                "CourseNum":"102562030"
            },
            {
                "CourseName":"经济法（全英文）",
                "CourseNum":"102552020"
            }
        ]
    },
    {
        "ID":"103-1-1",
        "CollegeNum":103,
        "CollegeName":"法学院",
        "PlanNum":1,
        "PlanName":"LEGAL HIGH",
        "PlanStage":1,
        "Auxli":[],
        "SubPlan":[
            {"PlanName":"法学"},
            {"PlanName":"法学（卓越法律人才计划涉外实验班）"}
        ],
        "CourseInfo":[
            {
                "CourseName":"法学导论",
                "CourseNum":"103008020"
            },
            {
                "CourseName":"宪法",
                "CourseNum":"103060030"
            },
            {
                "CourseName":"刑法总论",
                "CourseNum":"103066040"
            },
            {
                "CourseName":"民法总论",
                "CourseNum":"103124030"
            },
            {
                "CourseName":"社会调查",
                "CourseNum":"103363000"
            },
            {
                "CourseName":"大学文科数学",
                "CourseNum":"201261040"
            },
            {
                "CourseName":"法学文献检索与论文写作",
                "CourseNum":"103352010"
            }
        ]
    },
    {
        "ID":"104-1-1",
        "CollegeName":"文学与新闻学院",
        "CollegeNum":104,
        "PlanName":"國學發微",
        "PlanNum":1,
        "PlanStage":1,
        "Auxli":[],
        "SubPlan":[
            {"PlanName":"汉语言文学"},
            {"PlanName":"汉语言文学（基地班）"},
            {"PlanName":"汉语国际教育"}
        ],
        "CourseInfo":[
            {
                "CourseName":"现代汉语-1",
                "CourseNum":"104131040"
            },
            {
                "CourseName":"影视艺术概论",
                "CourseNum":"104165030"
            },
            {
                "CourseName":"古代汉语1",
                "CourseNum":"104238050"
            },
            {
                "CourseName":"文学理论1",
                "CourseNum":"104240030"
            },
            {
                "CourseName":"写作理论与实践",
                "CourseNum":"104242030"
            },
            {
                "CourseName":"文化人类学",
                "CourseNum":"104256030"
            }
        ]
    },
    { 
        "ID":"104-2-1",
        "CollegeName":"文学与新闻学院",
        "CollegeNum":104,
        "PlanName":"新聞與傳媒",
        "PlanNum":2,
        "PlanStage":1,
        "Auxli":[],
        "SubPlan":[
            {"PlanName":"编辑出版学"},
            {"PlanName":"广播电视学"},
            {"PlanName":"广告学"},
            {"PlanName":"网络与新媒体"},
            {"PlanName":"新闻学"}
        ],
        "CourseInfo":[
            {
                "CourseName":"编辑出版学概论",
                "CourseNum":"104008030"
            },
            {
                "CourseName":"广播电视概论",
                "CourseNum":"104036030"
            },
            {
                "CourseName":"广告学概论",
                "CourseNum":"104059030"
            },
            {
                "CourseName":"现代汉语B",
                "CourseNum":"104133020"
            },
            {
                "CourseName":"影视艺术概论",
                "CourseNum":"104165030"
            },
            {
                "CourseName":"写作理论与实践",
                "CourseNum":"104242030"
            },
            {
                "CourseName":"新闻学概论",
                "CourseNum":"104421040"
            },
            {
                "CourseName":"新媒体概论",
                "CourseNum":"104523030"
            }
        ]
    },
    {
        "ID":"105-1-1",
        "CollegeName":"外国语学院",
        "CollegeNum":105,
        "PlanName":"亚非拉统战司",
        "PlanNum":1,
        "PlanStage":1,
        "Auxli":[],
        "SubPlan":[
            {"PlanName":"波兰语（国际关系方向）"},
            {"PlanName":"波兰语（经济方向）"},
            {"PlanName":"俄语"},
            {"PlanName":"法语"},
            {"PlanName":"日语"},
            {"PlanName":"西班牙语"},
            {"PlanName":"英语"}
        ],
        "CourseInfo":[
            {
                "CourseName":"外国语文导论",
                "CourseNum":"105593020"
            },
            {
                "CourseName":"英语听力-1",
                "CourseNum":"105256020"
            },
            {
                "CourseName":"英语语音基础",
                "CourseNum":"105272020"
            },
            {
                "CourseName":"英语视听说-1",
                "CourseNum":"105254020"
            },
            {
                "CourseName":"英语语法",
                "CourseNum":"105269020"
            },
            {
                "CourseName":"综合英语1-语言与文化",
                "CourseNum":"105639060"
            },
            {
                "CourseName":"西方文化研究导论",
                "CourseNum":"105621020"
            },
            {
                "CourseName":"文学研究导论",
                "CourseNum":"105622020"
            },
            {
                "CourseName":"英语会话-交际口语",
                "CourseNum":"105631010"
            },
            {
                "CourseName":"初级西班牙语-1",
                "CourseNum":"105625080"
            },
            {
                "CourseName":"西班牙语语音",
                "CourseNum":"105626010"
            },
            {
                "CourseName":"欧洲文化 (全英文)",
                "CourseNum":"105612020"
            },
            {
                "CourseName":"西班牙语初级听力-1",
                "CourseNum":"105682020"
            },
            {
                "CourseName":"基础日语-1",
                "CourseNum":"105138080"
            },
            {
                "CourseName":"日语会话-1",
                "CourseNum":"105175020"
            },
            {
                "CourseName":"英语外来词汇（全英文）",
                "CourseNum":"105391020"
            },
            {
                "CourseName":"日语视听说-1",
                "CourseNum":"105705020"
            },
            {
                "CourseName":"基础法语—1",
                "CourseNum":"105623080"
            },
            {
                "CourseName":"基础法语听力—1",
                "CourseNum":"105624020"
            },
            {
                "CourseName":"基础法语会话—1",
                "CourseNum":"105658020"
            },
            {
                "CourseName":"阅读与批评",
                "CourseNum":"105673020"
            },
            {
                "CourseName":"基础俄语-1",
                "CourseNum":"105134080"
            },
            {
                "CourseName":"俄语听力-1",
                "CourseNum":"105076020"
            },
            {
                "CourseName":"俄语会话-1",
                "CourseNum":"105057020"
            },
            {
                "CourseName":"俄罗斯国情",
                "CourseNum":"105049020"
            },
            {
                "CourseName":"波兰国家概况",
                "CourseNum":"105569020"
            },
            {
                "CourseName":"基础波语-1",
                "CourseNum":"105570100"
            },
            {
                "CourseName":"波语视听说-1",
                "CourseNum":"105620040"
            }
        ]
    },
    {
        "ID":"106-1-1",
        "CollegeName":"历史文化学院（旅游学院）",
        "CollegeNum":106,
        "PlanName":"書史通鑒",
        "PlanNum":1,
        "PlanStage":1,
        "Auxli":[],
        "SubPlan":[
            {"PlanName":"会展经济与管理"},
            {"PlanName":"考古学"},
            {"PlanName":"历史学（基地班）"},
            {"PlanName":"历史学"},
            {"PlanName":"旅游管理"},
            {"PlanName":"文物与博物馆学"}
        ],
        "CourseInfo":[
            {
                "CourseName":"管理学原理",
                "CourseNum":"106037030"
            },
            {
                "CourseName":"微观经济学",
                "CourseNum":"106629030"
            },
            {
                "CourseName":"社会学",
                "CourseNum":"106592020"
            },
            {
                "CourseName":"旅游学基础",
                "CourseNum":"106077030"
            },
            {
                "CourseName":"古代汉语-1",
                "CourseNum":"106033030"
            },
            {
                "CourseName":"中国古代史（上）",
                "CourseNum":"106134040"
            },
            {
                "CourseName":"世界上古史",
                "CourseNum":"106100030"
            },
            {
                "CourseName":"考古学导论",
                "CourseNum":"106049020"
            }
        ]
    },
    {
        "ID":"108-1-1",
        "CollegeName":"国际关系学院",
        "CollegeNum":108,
        "PlanName":"政治与外交",
        "PlanNum":1,
        "PlanStage":1,
        "Auxli":[],
        "SubPlan":[
            {"PlanName":"国际政治"}
        ],
        "CourseInfo":[
            {
                "CourseName":"国际政治概论",
                "CourseNum":"108002030"
            },
            {
                "CourseName":"政治学原理",
                "CourseNum":"108001030"
            },
            {
                "CourseName":"当代中国政府与政治",
                "CourseNum":"108009030"
            },
            {
                "CourseName":"当代国际关系",
                "CourseNum":"108064020"
            },
            {
                "CourseName":"当代中国外交政策",
                "CourseNum":"108069020"
            },
            {
                "CourseName":"专业英语",
                "CourseNum":"108023030"
            }
        ]
    },
    {
        "ID":"201-1-1",
        "CollegeName":"数学学院",
        "CollegeNum":201,
        "PlanName":"与数分的热恋",
        "PlanNum":1,
        "PlanStage":1,
        "Auxli":[],
        "SubPlan":[
            {"PlanName":"数学（基地班）"},
            {"PlanName":"数学与应用数学（基础方向）"},
            {"PlanName":"数学与应用数学（金融方向）"},
            {"PlanName":"数学与应用数学（试验班）"},
            {"PlanName":"统计学（数据科学与大数据技术方向）"},
            {"PlanName":"统计学"},
            {"PlanName":"信息与计算科学"}
        ],
        "CourseInfo":[
            {
                "CourseName":"解析几何",
                "CourseNum":"201127040"
            },
            {
                "CourseName":"数学分析-1",
                "CourseNum":"201048050"
            },
            {
                "CourseName":"高等代数-1（双语）",
                "CourseNum":"201097050"
            },
            {   
                "CourseName":"基础英语写作-1",
                "CourseNum":"603195020"
            }
        ]
    },
    {
        "ID":"202-1-1",
        "CollegeName":"物理科学与技术学院（核科学与工程技术学院）",
        "CollegeNum":202,
        "PlanName":"永远不要自学量子力学（不自量力）",
        "PlanNum":1,
        "PlanStage":1,
        "Auxli":[],
        "SubPlan":[
            {"PlanName":"核工程与核技术"},
            {"PlanName":"微电子科学与工程"},
            {"PlanName":"物理学（基地班）"},
            {"PlanName":"物理学（试验班）"},
            {"PlanName":"物理学"}
        ],
        "CourseInfo":[
            {
                "CourseName":"力学",
                "CourseNum":"202148030"
            },
            {
                "CourseName":"物理学导论",
                "CourseNum":"202444010"
            },
            {
                "CourseName":"力学专题研讨",
                "CourseNum":"202275010"
            },
            {
                "CourseName":"基础英语写作-1",
                "CourseNum":"603195020"
            },
            {
                "CourseName":"微电子学概论",
                "CourseNum":"202189010"
            },
            {
                "CourseName":"工程制图（Ⅰ）",
                "CourseNum":"302049030"
            },
            {
                "CourseName":"核工程与核技术概论",
                "CourseNum":"202234010"
            }
        ]
    },
    {
        "ID":"203-1-1",
        "CollegeName":"化学学院",
        "CollegeNum":203,
        "PlanName":"氢氦锂铍硼 碳氮氧氟氖",
        "PlanNum":1,
        "PlanStage":1,
        "Auxli":[],
        "SubPlan":[
            {"PlanName":"化学（基地班）"},
            {"PlanName":"化学（试验班）"},
            {"PlanName":"化学"},
            {"PlanName":"应用化学"}
        ],
        "CourseInfo":[
            {
                "CourseName":"无机化学（Ⅰ）-1",
                "CourseNum":"203087040"
            },
            {
                "CourseName":"无机化学实验（Ⅰ）-1",
                "CourseNum":"908026020"
            },
            {
                "CourseName":"基础英语写作-1",
                "CourseNum":"603195020"
            }
        ]
    },
    {
        "ID":"204-1-1",
        "CollegeName":"生命科学学院",
        "CollegeNum":204,
        "PlanName":"生物的世纪",
        "PlanNum":1,
        "PlanStage":1,
        "Auxli":[],
        "SubPlan":[
            {"PlanName":"生态学"},
            {"PlanName":"生物技术（基地班）"},
            {"PlanName":"生物技术"},
            {"PlanName":"生物科学（基地班）"},
            {"PlanName":"生物科学（试验班）"},
            {"PlanName":"生物科学"}
        ],
        "CourseInfo":[
            {
                "CourseName":"大学化学（Ⅱ）-1",
                "CourseNum":"203224020"
            },
            {
                "CourseName":"动物生物学",
                "CourseNum":"204013030"
            },
            {
                "CourseName":"基础英语写作-1",
                "CourseNum":"603195020"
            },
            {
                "CourseName":"普通生物学",
                "CourseNum":"204168040"
            },
            {
                "CourseName":"普通生物学实验",
                "CourseNum":"204169040"
            }
        ]
    },
    {
        "ID":"205-1-1",
        "CollegeName":"电子信息学院",
        "CollegeNum":205,
        "PlanName":"专业电信贴膜",
        "PlanNum":1,
        "PlanStage":1,
        "Auxli":[],
        "SubPlan":[
            {"PlanName":"电子科学与技术"},
            {"PlanName":"电子信息工程"},
            {"PlanName":"电子信息工程（卓越工程师班）"},
            {"PlanName":"电子信息科学与技术"},
            {"PlanName":"光电信息科学与工程"}
        ],
        "CourseInfo":[
            {
                "CourseName":"计算机程序设计基础",
                "CourseNum":"205243020"
            },
            {
                "CourseName":"信息科学技术导论",
                "CourseNum":"205244010"
            },
            {
                "CourseName":"电子实训基础",
                "CourseNum":"205253010"
            },
            {
                "CourseName":"机械制图及CAD",
                "CourseNum":"205249020"
            }
        ]
    },
    {
        "ID":"300-1-1",
        "CollegeName":"高分子科学与工程学院",
        "CollegeNum":300,
        "PlanName":"gay(高)分子科学",
        "PlanNum":1,
        "PlanStage":1,
        "Auxli":[],
        "SubPlan":[
            {"PlanName":"高分子材料与工程（卓越工程师班）"},
            {"PlanName":"高分子材料与工程"}
        ],
        "CourseInfo":[
            {
                "CourseName":"近代化学基础（Ⅱ）-1",
                "CourseNum":"308117020"
            },
            {
                "CourseName":"工科化学实验（Ⅱ）-1",
                "CourseNum":"908010010"
            },
            {
                "CourseName":"工程制图（Ⅰ）",
                "CourseNum":"302049030"
            },
            {
                "CourseName":"大学物理（理工）Ⅲ-1",
                "CourseNum":"202027020"
            }
        ]
    },
    {
        "ID":"301-1-1",
        "CollegeName":"材料科学与工程学院",
        "CollegeNum":301,
        "PlanName":"材料的力量",
        "PlanNum":1,
        "PlanStage":1,
        "Auxli":[],
        "SubPlan":[
            {"PlanName":"材料化学"},
            {"PlanName":"材料物理"},
            {"PlanName":"金属材料工程"},
            {"PlanName":"无机非金属材料工程"},
            {"PlanName":"新能源材料与器件"}
        ],
        "CourseInfo":[
            {
                "CourseName":"大学化学（Ⅲ）-1",
                "CourseNum":"203226030"
            },
            {
                "CourseName":"大学化学实验（Ⅱ）-1",
                "CourseNum":"908003020"
            },
            {
                "CourseName":"大学物理（理工）Ⅱ-1",
                "CourseNum":"202025030"
            },
            {
                "CourseName":"大学物理实验（理工）Ⅱ-1",
                "CourseNum":"202039020"
            }
        ]
    },
    {
        "ID":"301-2-1",
        "CollegeName":"材料科学与工程学院",
        "CollegeNum":301,
        "PlanName":"生物医学工程",
        "PlanNum":2,
        "PlanStage":1,
        "Auxli":[
            {
                "AuxCollegeNum":303,
                "AuxCollegeName":"电气信息学院",
                "AuxPlanName":"医学信息工程",
                "AuxPlanNum":"4385"
            }
        ],
        "SubPlan":[
            {"PlanName":"生物医学工程（生物材料与人工器官方向）"},
            {"PlanName":"生物医学工程（生物医学图像仪器、生物力学方向）"},
            {"PlanName":"医学信息工程"}
        ],
        "CourseInfo":[
            {
                "CourseName":"工科化学实验（Ⅰ）-1",
                "CourseNum":"908007010"
            },
            {
                "CourseName":"生物医学工程概论",
                "CourseNum":"301377020"
            },
            {
                "CourseName":"大学物理（理工）Ⅱ-1",
                "CourseNum":"202025030"
            },
            {
                "CourseName":"大学物理实验（理工）Ⅱ-1",
                "CourseNum":"202039020"
            },
            {
                "CourseName":"近代化学基础（Ⅱ）-1",
                "CourseNum":"308117020"
            },
            {
                "CourseName":"认识实习",
                "CourseNum":"301095010"
            },
            {
                "CourseName":"计算机基础及C语言程序设计",
                "CourseNum":"303344020"
            },
            {
                "CourseName":"计算机基础及C语言程序设计上机实践",
                "CourseNum":"303355015"
            }
        ]
    },
    {
        "ID":"302-1-1",
        "CollegeName":"制造科学与工程学院",
        "CollegeNum":302,
        "PlanName":"制出奇迹，造出未来",
        "PlanNum":1,
        "PlanStage":1,
        "SubPlan":[
            {"PlanName":"材料成型及控制工程（卓越工程师班）"},
            {"PlanName":"材料成型及控制工程"},
            {"PlanName":"测控技术与仪器"},
            {"PlanName":"工业设计"},
            {"PlanName":"机械设计制造及其自动化（卓越工程师班）"},
            {"PlanName":"机械设计制造及其自动化"}
        ],
        "CourseInfo":[
            {
                "CourseName":"机械制图 Ⅰ",
                "CourseNum":"302328060"
            },
            {
                "CourseName":"平面构成",
                "CourseNum":"302339020"
            },
            {
                "CourseName":"世界著名博物馆艺术经典（跨校共建）",
                "CourseNum":"106563020"
            },
            {
                "CourseName":"工业产品素描与环境表达",
                "CourseNum":"302185040"
            }
        ]
    },
    {
        "ID":"303-1-1",
        "CollegeName":"电气信息学院",
        "CollegeNum":303,
        "PlanName":"国家电网",
        "PlanNum":1,
        "PlanStage":1,
        "Auxli":[],
        "SubPlan":[
            {"PlanName":"电气工程及其自动化"},
            {"PlanName":"通信工程"},
            {"PlanName":"自动化"}
        ],  
        "CourseInfo":[
            {
                "CourseName":"计算机基础及C语言程序设计",
                "CourseNum":"303344020"
            },
            {
                "CourseName":"计算机基础及C语言程序设计上机实践",
                "CourseNum":"303355015"
            },
            {
                "CourseName":"大学物理（理工）Ⅲ-1",
                "CourseNum":"202027020"
            },
            {
                "CourseName":"大学物理实验（理工）Ⅲ-1",
                "CourseNum":"202041020"
            },
            {
                "CourseName":"工程制图（Ⅰ）",
                "CourseNum":"302049030"
            },
            {
                "CourseName":"信息检索与利用（理工类）",
                "CourseNum":"902001020"
            }
        ]
    },
    {
        "ID":"304-1-1",
        "CollegeName":"计算机学院",
        "CollegeNum":304,
        "PlanName":"计算机，从入门到精通",
        "PlanNum":1,
        "PlanStage":1,
        "Auxli":[],
        "SubPlan":[
            {"PlanName":"计算机科学与技术（试验班）"},
            {"PlanName":"计算机科学与技术（卓越工程师班）"},
            {"PlanName":"计算机科学与技术"},
            {"PlanName":"物联网工程"}
        ],
        "CourseInfo":[
            {
                "CourseName":"基础英语写作-1",
                "CourseNum":"603195020"
            },
            {
                "CourseName":"数字逻辑（双语）",
                "CourseNum":"304131030"
            },
            {
                "CourseName":"数字逻辑实验",
                "CourseNum":"304202010"
            },
            {
                "CourseName":"高级语言程序设计-Ⅰ",
                "CourseNum":"304023040"
            },
            {
                "CourseName":"UNIX操作系统",
                "CourseNum":"304152020"
            },
            {
                "CourseName":"计算机导论",
                "CourseNum":"304201020"
            }
        ]
    },
    {
        "ID":"305-1-1",
        "CollegeName":"建筑与环境学院",
        "CollegeNum":305,
        "PlanName":"建筑与环境",
        "PlanNum":1,
        "PlanStage":1,
        "Auxli":[],
        "SubPlan":[
            {"PlanName":"给排水科学与工程"},
            {"PlanName":"工程力学"},
            {"PlanName":"工程造价"},
            {"PlanName":"土木工程"},
            {"PlanName":"城乡规划"},
            {"PlanName":"风景园林"},
            {"PlanName":"环境工程"},
            {"PlanName":"环境科学"},
            {"PlanName":"建筑环境与能源应用工程"},
            {"PlanName":"建筑学"}
        ],
        "CourseInfo":[
            {
                "CourseName":"美术-1",
                "CourseNum":"305977040"
            },
            {
                "CourseName":"设计基础-1",
                "CourseNum":"305914080"
            },
            {
                "CourseName":"美术实习-1",
                "CourseNum":"305499010"
            },
            {
                "CourseName":"认知实习",
                "CourseNum":"305915010"
            },
            {
                "CourseName":"建筑概论",
                "CourseNum":"305502020"
            },
            {
                "CourseName":"土建工程概论",
                "CourseNum":"305611010"
            },
            {
                "CourseName":"画法几何与工程制图（1）",
                "CourseNum":"305610030"
            },
            {
                "CourseName":"C语言程序设计（基础）",
                "CourseNum":"909023020"
            },
            {
                "CourseName":"力学认识实习",
                "CourseNum":"305976010"
            },
            {
                "CourseName":"工程伦理学",
                "CourseNum":"305966010"
            },
            {
                "CourseName":"工程力学导论",
                "CourseNum":"305079010"
            },
            {
                "CourseName":"现代制造技术基础训练",
                "CourseNum":"905007030"
            },
            {
                "CourseName":"大学物理（理工）Ⅲ-1",
                "CourseNum":"202027020"
            },
            {
                "CourseName":"环境学导论",
                "CourseNum":"305612020"
            },
            {
                "CourseName":"近代化学基础（Ⅰ）-1",
                "CourseNum":"308114030"
            },
            {
                "CourseName":"基础生物学",
                "CourseNum":"305136020"
            },
            {
                "CourseName":"工科化学实验（Ⅰ）-1",
                "CourseNum":"908007010"
            }
        ]
    },
    {
        "ID":"306-1-1",
        "CollegeName":"水利水电学院",
        "CollegeNum":306,
        "PlanName":"水利水电，基情无限",
        "PlanNum":1,
        "PlanStage":1,
        "Auxli":[],
        "SubPlan":[
            {"PlanName":"能源与动力工程"},
            {"PlanName":"农业水利工程"},
            {"PlanName":"水利水电工程（卓越工程师班）"},
            {"PlanName":"水利水电工程"},
            {"PlanName":"水文与水资源工程"},
            {"PlanName":"土木工程（地下工程方向）"}
        ],
        "CourseInfo":[
            {
                "CourseName":"水利土木工程概论",
                "CourseNum":"306127010"
            },
            {
                "CourseName":"工程生态环境影响概论",
                "CourseNum":"306334010"
            },
            {
                "CourseName":"认识实习",
                "CourseNum":"306050010"
            },
            {
                "CourseName":"新能源概论",
                "CourseNum":"306335010"
            }
        ]
    },
    {
        "ID":"308-1-1",
        "CollegeName":"化学工程学院",
        "CollegeNum":308,
        "PlanName":"化工",
        "PlanNum":1,
        "PlanStage":1,
        "Auxli":[],
        "SubPlan":[
            {"PlanName":"安全工程"},
            {"PlanName":"过程装备与控制工程"},
            {"PlanName":"化学工程与工艺"},
            {"PlanName":"生物工程"},
            {"PlanName":"冶金工程"},
            {"PlanName":"制药工程"}
        ],
        "CourseInfo":[
            {
                "CourseName":"化工制图",
                "CourseNum":"308098020"
            },
            {
                "CourseName":"近代化学基础（Ⅰ）-1",
                "CourseNum":"308114030"
            },
            {
                "CourseName":"工科化学实验（Ⅰ）-1",
                "CourseNum":"908007010"
            },
            {
                "CourseName":"化工概论",
                "CourseNum":"308062020"
            },
            {
                "CourseName":"制药工程导论",
                "CourseNum":"308233010"
            },
            {
                "CourseName":"冶金技术进展",
                "CourseNum":"308193020"
            }
        ]
    },
    {
        "ID":"309-1-1",
        "CollegeName":"轻纺与食品学院",
        "CollegeNum":309,
        "PlanName":"轻纺与食品",
        "PlanNum":1,
        "PlanStage":1,
        "Auxli":[],
        "SubPlan":[
            {"PlanName":"纺织工程"},
            {"PlanName":"服装与服饰设计"},
            {"PlanName":"轻化工程（革制品设计方向）（卓越工程师班）"},
            {"PlanName":"轻化工程（革制品设计方向）"},
            {"PlanName":"轻化工程（皮革工程方向）（卓越工程师班）"},
            {"PlanName":"轻化工程（皮革工程方向）"},
            {"PlanName":"生物工程（轻工生物技术方向）"},
            {"PlanName":"食品科学与工程（卓越工程师班）"},
            {"PlanName":"食品科学与工程"}
        ],
        "CourseInfo":[
            {
                "CourseName":"近代化学基础（Ⅰ）-1",
                "CourseNum":"308114030"
            },
            {
                "CourseName":"大学物理（理工）Ⅲ-1",
                "CourseNum":"202027020"
            },
            {
                "CourseName":"大学物理实验（理工）Ⅲ-1",
                "CourseNum":"202041020"
            },
            {
                "CourseName":"工科化学实验（IV）-1",
                "CourseNum":"908050010"
            },
            {
                "CourseName":"设计素描",
                "CourseNum":"309112040"
            },
            {
                "CourseName":"图案与设计构成",
                "CourseNum":"309157040"
            },
            {
                "CourseName":"纺织与服装概论",
                "CourseNum":"309448020"
            },
            {
                "CourseName":"制衣工艺基础训练",
                "CourseNum":"309460020"
            }
        ]
    },
    {
        "ID":"311-1-1",
        "CollegeName":"软件学院",
        "CollegeNum":311,
        "PlanName":"软件开发",
        "PlanNum":1,
        "PlanStage":1,
        "Auxli":[],
        "SubPlan":[
            {"PlanName":"软件工程（英语）"},
            {"PlanName":"软件工程"}
        ],
        "CourseInfo":[
            {
                "CourseName":"程序设计基础",
                "CourseNum":"311230030"
            },
            {
                "CourseName":"计算机系统导论",
                "CourseNum":"311231030"
            }
        ]
    },
    {
        "ID":"313-1-1",
        "CollegeName":"空天科学与工程学院",
        "CollegeNum":313,
        "PlanName":"飞行器与航天",
        "PlanNum":1,
        "PlanStage":1,
        "Auxli":[],
        "SubPlan":[
          {"PlanName":"飞行器控制与信息工程"},
          {"PlanName":"航空航天工程"}
        ],
        "CourseInfo":[
            {
                "CourseName":"机械制图（Ⅱ）-1",
                "CourseNum":"302077020"
            },
            {
                "CourseName":"航空航天概论",
                "CourseNum":"313001020"
            }
        ]
    },
    {
        "ID":"314-1-1",
        "CollegeName":"网络空间安全学院",
        "CollegeNum":314,
        "PlanName":"黑客，白帽修炼手册",
        "PlanNum":1,
        "PlanStage":1,
        "Auxli":[],
        "SubPlan":[
            {"PlanName":"网络空间安全"}
        ],
        "CourseInfo":[
            {
                "CourseName":"计算机系统导论",
                "CourseNum":"314032030"
            },
            {
                "CourseName":"程序设计基础",
                "CourseNum":"314031040"
            },
            {
                "CourseName":"新生专业研讨课（网络空间安全导论）",
                "CourseNum":"314030010"
            }
        ]
    },
    {
        "ID":"401-1-1",
        "CollegeName":"公共管理学院",
        "CollegeNum":401,
        "PlanName":"公共与管理",
        "PlanNum":1,
        "PlanStage":1,
        "Auxli":[],
        "SubPlan":[
            {"PlanName":"档案学"},
            {"PlanName":"公共事业管理"},
            {"PlanName":"劳动与社会保障"},
            {"PlanName":"社会工作"},
            {"PlanName":"土地资源管理"},
            {"PlanName":"信息管理与信息系统"},
            {"PlanName":"信息资源管理"},
            {"PlanName":"行政管理"}
        ],
        "CourseInfo":[
            {
                "CourseName":"管理学原理",
                "CourseNum":"401067030"
            },
            {
                "CourseName":"信息资源管理基础",
                "CourseNum":"401496030"
            },
            {
                "CourseName":"档案学概论",
                "CourseNum":"401024020"
            },
            {
                "CourseName":"政治学基础",
                "CourseNum":"401402030"
            },
            {
                "CourseName":"社会学概论",
                "CourseNum":"401129030"
            },
            {
                "CourseName":"社会工作导论",
                "CourseNum":"401261030"
            },
            {
                "CourseName":"社会工作理论",
                "CourseNum":"401268030"
            },
            {
                "CourseName":"信息管理导论",
                "CourseNum":"401342020"
            }
        ]
    },
    {
        "ID":"401-2-1",
        "CollegeName":"公共管理学院",
        "CollegeNum":401,
        "PlanName":"哲学",
        "PlanNum":2,
        "PlanStage":1,
        "Auxli":[],
        "SubPlan":[
            {"PlanName":"哲学"}
        ],
        "CourseInfo":[
            {
                "CourseName":"中国哲学史1",
                "CourseNum":"401298030"
            },
            {
                "CourseName":"西方哲学史1",
                "CourseNum":"401299030"
            },
            {
                "CourseName":"古代汉语",
                "CourseNum":"401058030"
            },
            {
                "CourseName":"逻辑学导论",
                "CourseNum":"401295030"
            },
            {
                "CourseName":"哲学导论",
                "CourseNum":"401297030"
            }
        ]
    },
    {
        "ID":"402-1-1",
        "CollegeName":"商学院",
        "CollegeNum":402,
        "PlanName":"创造CEO",
        "PlanNum":1,
        "PlanStage":1,
        "Auxli":[],
        "SubPlan":[
            {"PlanName":"财务管理"},
            {"PlanName":"电子商务"},
            {"PlanName":"工程管理"},
            {"PlanName":"工商管理"},
            {"PlanName":"工业工程"},
            {"PlanName":"管理科学"},
            {"PlanName":"会计学"},
            {"PlanName":"人力资源管理（高水平运动员）"},
            {"PlanName":"人力资源管理"},
            {"PlanName":"市场营销"}
        ],
        "CourseInfo":[
            {
                "CourseName":"管理学原理（Ⅰ）",
                "CourseNum":"402083030"
            },
            {
                "CourseName":"基础会计学",
                "CourseNum":"402106030"
            },
            {
                "CourseName":"市场营销",
                "CourseNum":"402174030"
            }
        ]
    },
    {
        "ID":"501-1-1",
        "CollegeName":"华西基础医学与法医学院",
        "CollegeNum":501,
        "PlanName":"基础医学与法医学",
        "PlanNum":1,
        "PlanStage":1,
        "Auxli":[],
        "SubPlan":[
            {"PlanName":"法医学"},
            {"PlanName":"基础医学（基地班）"}
        ],
        "CourseInfo":[
            {
                "CourseName":"法医学概论",
                "CourseNum":"501025010"
            },
            {
                "CourseName":"大学化学实验（Ⅲ）",
                "CourseNum":"908005020"
            },
            {
                "CourseName":"大学化学（Ⅳ）",
                "CourseNum":"203010040"
            },
            {
                "CourseName":"逻辑学导论",
                "CourseNum":"401295030"
            },
            {
                "CourseName":"医学生物学（Ⅰ）",
                "CourseNum":"204094040"
            },
            {
                "CourseName":"哲学导论",
                "CourseNum":"401297030"
            },
            {
                "CourseName":"新生研讨课（基础医学导论）",
                "CourseNum":"501175010"
            },
            {
                "CourseName":"大学物理（医学物理）Ⅰ",
                "CourseNum":"202032040"
            },
            {
                "CourseName":"大学物理实验（医学）",
                "CourseNum":"202043020"
            }
        ]
    },
    {
        "ID":"502-1-1",
        "CollegeName":"华西临床医学院",
        "CollegeNum":502,
        "PlanName":"临床医学",
        "PlanNum":1,
        "PlanStage":1,
        "Auxli":[],
        "SubPlan":[
            {"PlanName":"康复治疗学（呼吸治疗方向）"},
            {"PlanName":"康复治疗学（假肢矫形方向）"},
            {"PlanName":"康复治疗学（听力与言语康复方向）"},
            {"PlanName":"康复治疗学（物理治疗方向）"},
            {"PlanName":"康复治疗学（作业治疗方向）"},
            {"PlanName":"临床医学（八年制）"},
            {"PlanName":"临床医学"},
            {"PlanName":"眼视光学"}
        ],
        "CourseInfo":[
            {
                "CourseName":"医学生物学（Ⅰ）",
                "CourseNum":"204094040"
            },
            {
                "CourseName":"大学物理（医学物理）Ⅱ",
                "CourseNum":"202033030"
            },
            {
                "CourseName":"有机化学（Ⅶ）",
                "CourseNum":"203122020"
            },
            {
                "CourseName":"有机化学实验（Ⅴ）",
                "CourseNum":"908024010"
            },
            {
                "CourseName":"系统解剖学（Ⅲ）",
                "CourseNum":"501092040"
            },
            {
                "CourseName":"临床医学导论-1（新生入学讨论）",
                "CourseNum":"502392010"
            },
            {
                "CourseName":"大学物理实验（医学）",
                "CourseNum":"202043020"
            }
        ]
    },
    {
        "ID":"502-2-1",
        "CollegeName":"华西临床医学院",
        "CollegeNum":502,
        "PlanName":"医学技术",
        "PlanNum":2,
        "PlanStage":1,
        "Auxli":[],
        "SubPlan":[
            {"PlanName":"医学检验技术"},
            {"PlanName":"医学影像技术（超声医学技术方向）"},
            {"PlanName":"医学影像技术（放射治疗技术方向）"},
            {"PlanName":"医学影像技术"}
        ],
        "CourseInfo":[
            {
                "CourseName":"医学生物学（Ⅱ）",
                "CourseNum":"204095030"
            },
            {
                "CourseName":"大学物理（医学物理）Ⅱ",
                "CourseNum":"202033030"
            },
            {
                "CourseName":"有机化学（Ⅶ）",
                "CourseNum":"203122020"
            },
            {
                "CourseName":"有机化学实验（Ⅴ）",
                "CourseNum":"908024010"
            },
            {
                "CourseName":"系统解剖学（Ⅲ）",
                "CourseNum":"501092040"
            }
        ]
    },
    {
        "ID":"502-3-1",
        "CollegeName":"华西临床医学院",
        "CollegeNum":502,
        "PlanName":"护理学",
        "PlanNum":3,
        "PlanStage":1,
        "Auxli":[],
        "SubPlan":[
            {"PlanName":"护理学（助产方向）"},
            {"PlanName":"护理学"}
        ],
        "CourseInfo":[
            {
                "CourseName":"组织学与胚胎学（Ⅲ）",
                "CourseNum":"501113020"
            },
            {
                "CourseName":"系统解剖学（Ⅲ）",
                "CourseNum":"501092040"
            },
            {
                "CourseName":"护理学导论",
                "CourseNum":"502063020"
            }
        ]
    },
    {
        "ID":"503-1-1",
        "CollegeName":"华西口腔医学院",
        "CollegeNum":503,
        "PlanName":"口腔医学",
        "PlanNum":1,
        "PlanStage":1,
        "Auxli":[],
        "SubPlan":[
            {"PlanName":"口腔医学"},
            {"PlanName":"临床医学（口腔医学方向）"}
        ],
        "CourseInfo":[
            {
                "CourseName":"医学生物学（Ⅰ）",
                "CourseNum":"204094040"
            },
            {
                "CourseName":"口腔医学导论（Ⅰ）",
                "CourseNum":"503039010"
            },
            {
                "CourseName":"口腔探究性学习-1",
                "CourseNum":"503032010"
            }
        ]
    },
    {
        "ID":"504-1-1",
        "CollegeName":"华西公共卫生学院",
        "CollegeNum":504,
        "PlanName":"公共卫生",
        "PlanNum":1,
        "PlanStage":1,
        "Auxli":[],
        "SubPlan":[
            {"PlanName":"食品卫生与营养学"},
            {"PlanName":"卫生检验与检疫"},
            {"PlanName":"预防医学"}
        ],
        "CourseInfo":[
            {
                "CourseName":"大学化学（Ⅴ）",
                "CourseNum":"203170020"
            },
            {
                "CourseName":"系统解剖学（Ⅲ）",
                "CourseNum":"501092040"
            },
            {
                "CourseName":"组织学与胚胎学（Ⅲ）",
                "CourseNum":"501113020"
            },
            {
                "CourseName":"有机化学（Ⅵ）",
                "CourseNum":"203121030"
            },
            {
                "CourseName":"大学化学实验（Ⅴ）",
                "CourseNum":"908048010"
            },
            {
                "CourseName":"无机化学（Ⅱ）",
                "CourseNum":"203089040"
            },
            {
                "CourseName":"无机化学实验（Ⅱ）",
                "CourseNum":"908014020"
            },
            {
                "CourseName":"组织学与胚胎学实验（Ⅲ）",
                "CourseNum":"501117010"
            }
        ]
    },
    {
        "ID":"505-1-1",
        "CollegeName":"华西药学院",
        "CollegeNum":505,
        "PlanName":"药学",
        "PlanNum":1,
        "PlanStage":1,
        "Auxli":[],
        "SubPlan":[
            {"PlanName":"临床药学"},
            {"PlanName":"药学"}
        ],
        "CourseInfo":[
            {
                "CourseName":"无机化学实验（Ⅱ）",
                "CourseNum":"908014020"
            },
            {
                "CourseName":"药学概论",
                "CourseNum":"505136010"
            },
            {
                "CourseName":"大学物理（药学物理）",
                "CourseNum":"202031040"
            },
            {
                "CourseName":"无机化学（Ⅲ）",
                "CourseNum":"203090030"
            },
            {
                "CourseName":"临床药学导论",
                "CourseNum":"505084020"
            }
        ]
    }
]